starway/.gitignore
starway/__init__.py
starway/_bindings.cpython-313-x86_64-linux-gnu.so
starway/_bindings.pyi
starway/bench.py
starway/py.typed
starway/test.py
starway/benchmarks/__init__.py
starway/benchmarks/scenarios.py
starway-0.6.0.dist-info/METADATA
starway-0.6.0.dist-info/WHEEL
starway-0.6.0.dist-info/RECORD
