Metadata-Version: 2.2
Name: starway
Version: 0.6.0
Summary: Starway UCX P2P communication lib.
Author-Email: Clouder0 <clouder0@outlook.com>
Requires-Python: >=3.10
Requires-Dist: numpy>=2.0.0
